odoo9_addon_pos_session_summary-9.0.1.0.0.99.dev14-py3.6-nspkg.pth
odoo_addons/pos_session_summary/README.rst
odoo_addons/pos_session_summary/__init__.py
odoo_addons/pos_session_summary/__openerp__.py
odoo_addons/pos_session_summary/i18n/ca.po
odoo_addons/pos_session_summary/i18n/es.po
odoo_addons/pos_session_summary/i18n/fr.po
odoo_addons/pos_session_summary/i18n/pos_session_summary.pot
odoo_addons/pos_session_summary/models/__init__.py
odoo_addons/pos_session_summary/models/account_bank_statement.py
odoo_addons/pos_session_summary/models/pos_session.py
odoo_addons/pos_session_summary/static/description/icon.png
odoo_addons/pos_session_summary/static/description/pos_session_list.png
odoo_addons/pos_session_summary/views/pos_session_view.xml
odoo9_addon_pos_session_summary-9.0.1.0.0.99.dev14.dist-info/METADATA
odoo9_addon_pos_session_summary-9.0.1.0.0.99.dev14.dist-info/WHEEL
odoo9_addon_pos_session_summary-9.0.1.0.0.99.dev14.dist-info/namespace_packages.txt
odoo9_addon_pos_session_summary-9.0.1.0.0.99.dev14.dist-info/top_level.txt
odoo9_addon_pos_session_summary-9.0.1.0.0.99.dev14.dist-info/RECORD
